sjm_tools/__init__.py
sjm_tools/qsjm.py
sjm_tools/sjm_tools.py
sjm_tools/example/template.py
sjm_tools/utils/sleep.py
sjm_tools-1.0.dist-info/LICENSE
sjm_tools-1.0.dist-info/METADATA
sjm_tools-1.0.dist-info/WHEEL
sjm_tools-1.0.dist-info/entry_points.txt
sjm_tools-1.0.dist-info/top_level.txt
sjm_tools-1.0.dist-info/RECORD
